{
    "of1a1": [
        -10393.0,
        0.0,
        0.0
    ],
    "of1a2": [
        0.0,
        0.0,
        0.0
    ],
    "of1a3": [
        0.0,
        0.0,
        0.0
    ],
    "of1a4": [
        0.0,
        0.0,
        0.0
    ],
    "of1a4b": [
        11234.0,
        0.0078125,
        74.0
    ],
    "of1a5": [
        0.0,
        0.0,
        0.0
    ],
    "of1a5b": [
        0.0,
        0.0,
        0.0
    ],
    "of1a6": [
        0.0,
        0.0,
        0.0
    ],
    "of2a1": [
        0.0,
        0.0,
        0.0
    ],
    "of2a1b": [
        0.0,
        0.0,
        0.0
    ],
    "of2a2": [
        11742.0,
        0.0,
        3748.0
    ],
    "of2a3": [
        0.0,
        0.0,
        0.0
    ],
    "of2a4": [
        0.0,
        323.63812255859375,
        0.0
    ],
    "of2a5": [
        0.0,
        0.0,
        0.0
    ],
    "of2a6": [
        0.0,
        0.0,
        0.0
    ],
    "of3a1": [
        950.0,
        0.0,
        2374.0
    ],
    "of3a1b": [
        0.0,
        0.0,
        0.0
    ],
    "of3a2": [
        0.0,
        0.0,
        0.0
    ],
    "of3a4": [
        0.0,
        0.0,
        0.0
    ],
    "of3a5": [
        0.0,
        0.0,
        0.0
    ],
    "of3a6": [
        0.0,
        0.0,
        0.0
    ],
    "of4a1": [
        0.0,
        0.0,
        0.0
    ],
    "of4a2": [
        0.0,
        0.0,
        0.0
    ],
    "of4a3": [
        0.0,
        0.0,
        0.0
    ],
    "of4a4": [
        0.0,
        0.0,
        0.0
    ],
    "of4a5": [
        0.0,
        0.0,
        0.0
    ],
    "of5a1": [
        0.0,
        0.0,
        0.0
    ],
    "of5a2": [
        0.0,
        0.0,
        0.0
    ],
    "of5a3": [
        0.0,
        0.0,
        0.0
    ],
    "of5a4": [
        0.0,
        0.0,
        0.0
    ],
    "of6a1": [
        0.0,
        0.0,
        0.0
    ],
    "of6a2": [
        0.0,
        0.0,
        0.0
    ],
    "of6a3": [
        0.0,
        0.0,
        0.0
    ],
    "of6a4": [
        0.0,
        0.0,
        0.0
    ],
    "of6a4b": [
        0.0,
        0.0,
        0.0
    ],
    "of6a5": [
        0.0,
        0.0,
        0.0
    ],
    "of7a0": [
        0.0,
        0.0,
        0.0
    ]
}